camel/__init__.py
camel/camel_model.py
camel/camel_modifier.py
camel/models/llama/configuration_llama.py
camel/models/llama/modeling_llama.py
camel/models/llama/modifier_llama.py
camel/utils/cache.py
camel/utils/choices.py
camel/utils/logits_precessor.py
camel/utils/tree.py
modifier-0.0.3.dist-info/LICENSE
modifier-0.0.3.dist-info/METADATA
modifier-0.0.3.dist-info/WHEEL
modifier-0.0.3.dist-info/RECORD
